LICENSE.txt
README.md
setup.cfg
setup.py
grassmanntn/__init__.py
grassmanntn/arith.py
grassmanntn/example.py
grassmanntn/example_block.py
grassmanntn/gauge2d.py
grassmanntn/gauge2d_block.py
grassmanntn/param.py
grassmanntn.egg-info/PKG-INFO
grassmanntn.egg-info/SOURCES.txt
grassmanntn.egg-info/dependency_links.txt
grassmanntn.egg-info/requires.txt
grassmanntn.egg-info/top_level.txt